{
  "label": "Words",
  "stack": "Words",
  "data": [
    {
      "location": "13",
      "value": 709048
    },
    {
      "location": "31",
      "value": 255033
    },
    {
      "location": "94",
      "value": 686171
    },
    {
      "location": "93",
      "value": 1314097
    },
    {
      "location": "78",
      "value": 299341
    },
    {
      "location": "75",
      "value": 2694429
    },
    {
      "location": "77",
      "value": 246956
    },
    {
      "location": "91",
      "value": 589047
    },
    {
      "location": "92",
      "value": 437430
    },
    {
      "location": "95",
      "value": 367890
    },
    {
      "location": "57",
      "value": 73120
    },
    {
      "location": "67",
      "value": 123615
    },
    {
      "location": "21",
      "value": 19247
    },
    {
      "location": "30",
      "value": 45176
    },
    {
      "location": "76",
      "value": 102008
    },
    {
      "location": "25",
      "value": 32398
    },
    {
      "location": "60",
      "value": 54764
    },
    {
      "location": "84",
      "value": 9010
    },
    {
      "location": "42",
      "value": 25317
    },
    {
      "location": "69",
      "value": 279260
    },
    {
      "location": "35",
      "value": 116922
    },
    {
      "location": "59",
      "value": 164202
    },
    {
      "location": "34",
      "value": 131513
    },
    {
      "location": "28",
      "value": 20045
    },
    {
      "location": "38",
      "value": 50092
    },
    {
      "location": "74",
      "value": 26689
    },
    {
      "location": "33",
      "value": 140770
    },
    {
      "location": "45",
      "value": 66735
    },
    {
      "location": "49",
      "value": 39866
    },
    {
      "location": "14",
      "value": 24592
    },
    {
      "location": "12",
      "value": 3472
    },
    {
      "location": "6",
      "value": 65037
    },
    {
      "location": "1",
      "value": 16128
    },
    {
      "location": "44",
      "value": 123388
    },
    {
      "location": "68",
      "value": 22675
    },
    {
      "location": "27",
      "value": 15045
    },
    {
      "location": "51",
      "value": 19286
    },
    {
      "location": "65",
      "value": 8846
    },
    {
      "location": "71",
      "value": 26072
    },
    {
      "location": "18",
      "value": 41219
    },
    {
      "location": "66",
      "value": 18226
    },
    {
      "location": "54",
      "value": 25219
    },
    {
      "location": "83",
      "value": 19788
    },
    {
      "location": "63",
      "value": 1022
    },
    {
      "location": "2",
      "value": 17509
    },
    {
      "location": "43",
      "value": 638
    },
    {
      "location": "29",
      "value": 14967
    },
    {
      "location": "26",
      "value": 4320
    },
    {
      "location": "85",
      "value": 11226
    },
    {
      "location": "86",
      "value": 8870
    },
    {
      "location": "58",
      "value": 24636
    },
    {
      "location": "37",
      "value": 9021
    },
    {
      "location": "41",
      "value": 18418
    },
    {
      "location": "55",
      "value": 19510
    },
    {
      "location": "61",
      "value": 11461
    },
    {
      "location": "90",
      "value": 5391
    },
    {
      "location": "10",
      "value": 11482
    },
    {
      "location": "50",
      "value": 518
    }
  ]
}